passwordless/__init__.py
passwordless/delivery_methods.py
passwordless/login_url.py
passwordless/passwordless.py
passwordless/token_store.py
propjockey/__init__.py
propjockey/mailers.py
propjockey/notify.py
propjockey/propjockey.py
propjockey/util.py
propjockey/templates/index.html
propjockey/templates/layout.html
propjockey/templates/login.html
propjockey-0.1.0.dist-info/DESCRIPTION.rst
propjockey-0.1.0.dist-info/METADATA
propjockey-0.1.0.dist-info/RECORD
propjockey-0.1.0.dist-info/WHEEL
propjockey-0.1.0.dist-info/metadata.json
propjockey-0.1.0.dist-info/top_level.txt
