Metadata-Version: 2.0
Name: propjockey
Version: 0.1.0
Summary: Spinning property workflows. Taking requests.
Home-page: https://github.com/materialsproject/propjockey
Author: MP team
Author-email: matproj-develop@googlegroups.com
License: modified BSD
Platform: UNKNOWN
Classifier: Programming Language :: Python :: 2
Classifier: Programming Language :: Python :: 2.7
Classifier: Development Status :: 2 - Pre-Alpha
Classifier: Intended Audience :: Science/Research
Classifier: Intended Audience :: System Administrators
Classifier: Intended Audience :: Information Technology
Classifier: Operating System :: OS Independent
Classifier: Topic :: Other/Nonlisted Topic
Classifier: Topic :: Database :: Front-Ends
Classifier: Topic :: Scientific/Engineering
Requires-Dist: flask
Requires-Dist: pymongo
Requires-Dist: requests
Requires-Dist: toolz
Provides-Extra: prod_matsci
Requires-Dist: gunicorn; extra == 'prod_matsci'
Requires-Dist: pymatgen; extra == 'prod_matsci'
